Workbook

Sheet Criteria
A1: Screen | B1: ID | C1: Criterion | D1: Threshold | E1: Type | F1: Why it's there (investor rationale) | G1: What it adds to the thesis | H1: Verifiable now? | I1: Why not easy / caveat
A2: Core Compounders | B2: U | C2: Universe | D2: No funds/SPACs/REITs/shells; excludes banks, insurers, real estate, commodity producers, autos, airlines, telecom, utilities, media, ad agencies | E2: Universe | F2: Chris Hohn states that leaving out banks, airlines, wireless telecom, media and ad agencies means avoiding what he calls bad businesses, because they face heavy competition or, for banks, high leverage, so profits are fragile. A mentioned example: air travel grew about 5% a year for a century, yet airlines collectively made minimal profits. Pat Dorsey states that excluding industries like airlines, auto parts, life insurance and oil and gas means avoiding price takers, because a large part of their future is not under their control. No specific past example given. Terry Smith states that dropping low-return sectors makes sense because good-company sectors don't become bad ones and vice versa; low-return industries stay low. A mentioned example: the airline industry, which he says never makes an adequate return on capital. | G2: Only businesses that can have pricing power. | H2: Easy | I2: Uses SEC industry (SIC) code; codes can be coarse or outdated (manual override list exists).
A3: Core Compounders | B3: G1 | C3: History | D3: >= 8 years of data | E3: Data | F3: Dev Kantesaria states that a long record matters because a company only meets his bar for predictability if he is confident it stays dominant for at least the next 10 years, and he prefers business models that have already worked for decades. No specific past example given. Chris Hohn states that a long history is informative because "good companies stay good and bad companies stay bad": barriers to entry persist, though only if you judged quality right in the first place. No specific past example given. | G3: Proves durability. | H3: Easy
A4: Core Compounders | B4: G2 | C4: Recent report | D4: Last annual report <= 1.6 years old | E4: Data | F4: No investor source: old financial statements can hide a recent collapse, so the latest annual report must be current. | G4: Keeps the screen current. | H4: Easy | I4: Rare: some foreign (20-F) reports filed but not yet in SEC XBRL data -> flagged.
A5: Core Compounders | B5: G3 | C5: Size (revenue) | D5: Revenue >= $200M | E5: Size | F5: No investor source: very small filers have patchier data and are harder to own in meaningful size. | G5: Focus on established businesses. | H5: Easy
A6: Core Compounders | B6: G4 | C6: Consistent profits | D6: <= 1 operating-loss year in 10 | E6: Quality | F6: Dev Kantesaria states that steady profits signal predictability, which he will not give up, because he hates losing money and avoids anything that "could go down 90% tomorrow"; quality means growth and predictability together. A mentioned example: young software firms are too unpredictable, while Nestlé or Hershey are predictable but too slow. | G6: Predictability. | H6: Easy
A7: Core Compounders | B7: G5a | C7: High returns (median) | D7: 10-yr median ROIC >= 15% | E7: Quality | F7: Pat Dorsey states that a high return on capital for many years is the sign of a moat, because Morningstar's moat work started by studying every company earning over 15% on capital for over 15 years (numbers he calls arbitrary). He warns ROIC can mislead where investment is expensed. No specific past example given. Terry Smith states that a high return on capital is "the single most important thing", because over a long hold your return converges on what the business earns. A mentioned example: Munger's point that a business earning 6% on capital for 40 years returns about 6% even if bought at a huge discount. | G7: Moat evidence (core of the thesis). | H7: Easy | I7: Rare: debt in non-standard tags or D&A untagged -> flagged.
A8: Core Compounders | B8: G5b | C8: High returns (consistency) | D8: >= 80% of years with ROIC >= 10% | E8: Quality | F8: Terry Smith states that returns held year after year signal lasting quality, because "Good companies don't become bad companies by and large or vice versa". A mentioned example: in data back to 1966, high-ROE companies stayed clustered around 20%, still well above the low-return group decades later. Pat Dorsey states that returns that keep holding up show a moat at work, because a moat lengthens the time before returns on capital decline to the cost of capital, so the company can keep reinvesting at high rates. No specific past example given. | G8: Moat is persistent, not a spike. | H8: Easy
A9: Core Compounders | B9: G6 | C9: Growth | D9: 10-yr revenue CAGR >= 5% | E9: Growth | F9: Dev Kantesaria states that growth is half of quality, because a predictable company growing only 2-3% a year does not deliver strong long-term returns; he wants faster growth that is still predictable. A mentioned example: Nestlé and Hershey, which he calls extremely predictable but slow-growing. Pat Dorsey states that a reinvestment runway matters, because a company with an obvious place to put its cash is less likely to make a dumb acquisition or a badly timed buyback. A mentioned example: eBay, a great network-effect moat that ran out of room to grow once it had its market. Terry Smith states that growth is needed to reinvest cash at high returns, because high returns are wasted if the company is "landlocked" in a small niche or geography. No specific past example given. | G9: Runway to reinvest. | H9: Easy | I9: Rare: tag changes cause fake revenue jumps -> flagged.
A10: Core Compounders | B10: G7 | C10: Cash conversion | D10: FCF / net income >= 0.8 | E10: Quality | F10: Terry Smith states that profits must turn into cash, because his first test of a good company is a high return on capital in cash: cash delivered in a period divided by capital employed. A mentioned example: he put his own portfolio at about 25% on this measure (2022). Connor Haley states that free cash flow is a better guide than reported profits, because earnings and EBITDA "can be easily manipulated". No specific past example given. | G10: Earnings quality. | H10: Easy | I10: Rare: capex not in a standard tag -> estimated or flagged.
A11: Core Compounders | B11: G8 | C11: Balance sheet | D11: Net debt / operating cash flow <= 3x | E11: Safety | F11: Mala Gaonkar states that low debt matters because decent businesses she owned that were overlevered had much less room to maneuver when macro stress arrived; avoiding balance-sheet leverage, such as public LBOs, is one of her hard-learned lessons. A mentioned example: she names one such holding, spelled "Altis" in the captions, without further detail. Paul Singer states that surviving comes first, because big losses wreck judgment while intact capital lets you act in a crisis: "you make a buck you keep it". A mentioned example: he lost 88% of his parents' money on margin in 1974; in late 2008, "everything got cheap" for those with capital left. | G11: Survival / downside protection. | H11: Easy | I11: Rare: debt in non-standard tags or D&A untagged -> flagged.
A12: Core Compounders | B12: Flag | C12: Margin collapse | D12: TTM operating margin < half its 10-yr median | E12: Warning | F12: Pat Dorsey states that a moat shows up as returns that take a long time to fall to the cost of capital, so a sharp margin drop can mean the moat is weakening; but he warns margins can also fall because investment like sales and software development is expensed. No specific past example given. | G12: Stops buying a broken compounder. | H12: No | I12: Detected automatically; temporary vs permanent needs a human.
A13: Core Compounders | B13: Flag | C13: Revenue shrinking | D13: 3-yr revenue CAGR < 0 | E13: Warning | F13: Terry Smith states that shrinking revenue must be judged across the cycle, because he wants secular, not cyclical, growth: each peak and trough should be bigger than the last, though growth needn't come every year. No specific past example given. Dev Kantesaria states that a volume drop is acceptable only if it is temporary, because a toll collector keeps raising prices and earns more when volume returns, while pricing to hide secular volume decline can backfire. A mentioned example: FICO's mortgage-score volume fell for years while it raised those prices 100% one year and over 40% the next. | G13: Same. | H13: No | I13: Detected automatically; temporary vs permanent needs a human.
A14: Core Compounders | B14: Flag | C14: Lost money in 2008-09 | D14: Operating loss on falling sales in 2008-09 | E14: Warning | F14: Terry Smith states that a recession loss may expose cyclical rather than secular growth, because a real compounder's trough should still be bigger than its previous trough. No specific past example given. Stanley Druckenmiller states that profits holding up in a recession mean the stock is protected, because "if you have very good earnings in a recession and they're sustainable" the market eventually sees it. A mentioned example: in June 2023 he argued that if staples can rise in a recession, Nvidia could too, with orders and earnings up about 70% in a hard landing. | G14: Avoids mistaking a cycle for a moat. | H14: No | I14: Detected automatically; temporary vs permanent needs a human.
A15: Core Compounders | B15: V | C15: Valuation | D15: None (price-blind by design); P/E, EV/EBITDA, FCF yield and peer medians shown only | E15: Valuation | F15: Terry Smith states that judging quality before price is right, because investors spend almost all their effort on whether a stock is cheap and far too little on whether the business is high-grade, and long-run returns follow the business. A mentioned example: Munger's point that a business earning 18% on capital for 20-30 years wins even at an expensive-looking price. Dev Kantesaria states that price should not decide inclusion, because a great compounder's value growth overcomes overpaying by 10 or 15%, and precise valuation is "a silly exercise". A mentioned example: he bought S&P Global at $17.50 during the financial crisis; it is now over $500, compounding he says he never could have expected. | G15: Keeps great businesses on the list even when dear. | H15: n/a | I15: No 'cheap enough' test - see Valuation sheet.
A16: Core Compounders | B16: J | C16: Human / AI review | D16: Moat durability, switching costs, management and capital allocation, AI disruption, why mispriced | E16: Judgment | F16: Pat Dorsey states that moat durability needs human judgment, because "you can't screen for switching costs"; whether customers find it hard to switch is learned by talking to customers, ex-employees and salespeople. No specific past example given. Peter Thiel states that durability, not growth, drives most of a company's value, because growth is easy to measure today while whether a company still exists in a decade is hard to quantify. A mentioned example: about three-quarters of PayPal's value as of 2001 came from cash flows in 2011 and beyond. Connor Haley states that the review must ask why the stock might be mispriced, "the most important question in the investment process", because smart analysts with the same information usually price a stock fairly. No specific past example given. | G16: Decides whether the numbers reflect a real thesis. | H16: No | I16: Qualitative; not in financial data. Left to the AI review + you.
A17: Emerging Compounders | B17: U | C17: Universe | D17: Core universe, also minus commodity materials (chemicals, paper, building materials, non-metal mining) | E17: Universe | F17: Connor Haley states that leaving out commodity sectors means searching where lasting advantages are more common, because his team found energy, materials and financials rarely contain many businesses with real competitive edges. A mentioned example: Alta Fox's study of 104 multibaggers (2015-2020) excluded energy, materials and financials from the start. Terry Smith states that avoiding materials means avoiding a sector with persistently low returns, because returns on capital stay in place for decades and a low price does not turn a bad company into a good one. A mentioned example: in his sector data, materials sat with utilities, telecoms, transport, energy and retailing among the persistently low-return groups. | G17: Only potential niche winners. | H17: Easy | I17: Uses SEC industry (SIC) code; codes can be coarse or outdated (manual override list exists).
A18: Emerging Compounders | B18: E1 | C18: History | D18: >= 4 years of data | E18: Data | F18: No investor source: you need a few years of numbers before growth and margin trends can be measured at all. | G18: Makes trend rules meaningful. | H18: Easy
A19: Emerging Compounders | B19: E2 | C19: Recent report | D19: Last annual report <= 1.6 years old | E19: Data | F19: No investor source: a data-quality rule, because old annual numbers can hide a recent collapse. | G19: Keeps the screen current. | H19: Easy | I19: Rare: some foreign (20-F) reports filed but not yet in SEC XBRL data -> flagged.
A20: Emerging Compounders | B20: E3 | C20: Already profitable | D20: TTM and last-FY EBITDA > 0 | E20: Quality | F20: Connor Haley states that already having positive EBITDA means the company is a proven business, not a cash burner, because most big winners were past the profit turning point and were not losing money and diluting shareholders to survive. A mentioned example: in Alta Fox's study of 104 multibaggers (2015-2020), 88% already had positive EBITDA five years earlier. | G20: Cuts cash-burning stories. | H20: Easy | I20: Rare: D&A untagged -> EBIT used.
A21: Emerging Compounders | B21: E4 | C21: Fast growth | D21: 3-yr revenue CAGR >= 15% | E21: Growth | F21: Connor Haley states that fast revenue growth means the company has the engine multibaggers need, because the big winners were growth businesses whose rising sales and profits got the market to re-rate them. A mentioned example: in Alta Fox's 104-stock study the median winner grew revenue 21% a year and EBITDA 28%; even the 25th percentile grew revenue 14% a year. | G21: The growth engine. | H21: Easy
A22: Emerging Compounders | B22: E5 | C22: Growth not fading | D22: Latest year-to-date growth >= 8% (else last FY) | E22: Growth | F22: Alex Sacerdote states that growth still running today means the main risk is not playing out, because "the biggest reason people blow up in tech is they miss on revenue". A mentioned example: US electric-car adoption stalled near 10%, so Whale Rock's rating of that S-curve fell from 10 out of 10 to zero and it stopped owning Tesla. | G22: Catches slowdowns early. | H22: Partly | I22: Foreign filers file no quarterly reports -> uses last fiscal year (stale).
A23: Emerging Compounders | B23: E6 | C23: Gross margin | D23: Gross margin >= 35% | E23: Quality | F23: Connor Haley states that a healthy gross margin means there is room for profit to grow faster than sales, because a company needs enough gross profit on each sale before spreading fixed costs can lift its margins. A mentioned example: in Alta Fox's study, the median multibagger had gross margins in the mid-40s% and EBITDA margins just over 10% at the start. | G23: Operating-leverage potential. | H23: Easy | I23: Rare: no gross-profit line (services) -> no data.
A24: Emerging Compounders | B24: E7 | C24: Operating leverage | D24: EBITDA margin up over 3 yrs, or SG&A/revenue down | E24: Quality | F24: Connor Haley states that overhead falling as a share of sales means the company is reaching operating leverage, because costs growing slower than revenue lift margins, which is often when an undiscovered stock gets re-rated. A mentioned example: in Alta Fox's study, the median winner's SG&A fell 416 basis points of revenue and its EBITDA margin rose 753 basis points over five years. Alex Sacerdote states that rising margins on top of fast growth mean earnings can grow much faster than sales, because with S-curve adoption and a rising margin "your earnings don't grow linearly they grow exponentially". A mentioned example: Whale Rock bought Tesla around end-2019 and 2020, when a cheaper Model 3 made electric-car adoption take off. | G24: Proof the model scales. | H24: Easy
A25: Emerging Compounders | B25: E8 | C25: Little dilution | D25: Share count growth <= 3%/yr (3 yrs) | E25: Quality | F25: Connor Haley states that little dilution means growth reaches each existing share, because per-share value matters more than size, and the big winners were funding themselves instead of issuing stock to cover losses. A mentioned example: in Alta Fox's 104-stock study, the winners were proven concepts that were not losing millions and meaningfully diluting shareholders. Chris Davis states that a share count that does not rise means value builds up for each owner, because long-term compounding only reaches holders if the company is not handing out more slices of itself. A mentioned example: his 50-year study found lasting winners such as Exxon and Philip Morris tended to have share counts that did not go up. | G25: Per-share compounding. | H25: Partly | I25: No share history for recent IPOs/spin-offs and some foreign filers (~20 flagged).
A26: Emerging Compounders | B26: E9 | C26: Leverage | D26: Net debt / EBITDA <= 2.5x | E26: Safety | F26: Connor Haley states that modest debt means downside protection, because a strong balance sheet lets a small company get through a shock that could push a levered one toward bankruptcy. A mentioned example: in March 2020 Alta Fox sold a well-run restaurant stock that had just borrowed to buy another business right before COVID. Brian Gaines states that heavy debt turns the equity into "an option bet", because lenders, especially banks, can force a levered company into bankruptcy, so the share price no longer tracks business value. A mentioned example: Movie Gallery, with $1.1 billion of debt on about 30 million shares, which he described as an option bet. | G26: Downside protection. | H26: Easy | I26: Rare: debt in non-standard tags or D&A untagged -> flagged.
A27: Emerging Compounders | B27: E10 | C27: Size (market cap) | D27: Market cap >= $150M | E27: Tradeability | F27: Connor Haley states that a minimum size means avoiding the tiniest stocks, because Alta Fox's preference for high-quality businesses has worked better a bit higher up, where it has done much better in small, mid and large caps. A mentioned example: Alta Fox's worst market-cap bucket since inception has been micro caps, and its multibagger study only counted companies above $150M. | G27: Micro caps were the study's worst bucket. | H27: Partly | I27: Price x SEC share count. Unreliable for ADRs (ADR ratio unknown), multi-class shares or missing share counts -> 'check manually' (~150 ADRs last run).
A28: Emerging Compounders | B28: E11 | C28: Not already large | D28: Market cap <= $10B | E28: Size | F28: Connor Haley states that staying below about $10B means the company still has room to multiply, because Alta Fox likes small caps that grow into mid caps and mid caps that grow into large caps, and that growth drives the return. A mentioned example: Alta Fox's study of 104 multibaggers only looked at companies with market caps between $150M and $10B. | G28: Runway for a multibagger. | H28: Partly | I28: Price x SEC share count. Unreliable for ADRs (ADR ratio unknown), multi-class shares or missing share counts -> 'check manually' (~150 ADRs last run).
A29: Emerging Compounders | B29: E12 | C29: Valuation | D29: EV / EBITDA <= 20x | E29: Valuation | F29: Connor Haley states that a moderate EV/EBITDA means the thesis can work on profit growth alone, because "if your entire thesis rests on significant multiple expansion maybe it's not a great thesis". A mentioned example: in his study the median multibagger traded about 10x forward EBITDA five years earlier and re-rated to about 25x, with two-thirds of the return from multiple expansion. Chris Davis states that a reasonable starting multiple means your return is set by the business, because he assumes no re-rating: "We may get it, but it's nowhere in our models." A mentioned example: in 2026 his holdings at about 14x earnings offered a 7.5% earnings yield, versus about 3.8% for the market at 26x. | G29: Return comes from growth, not multiple expansion. | H29: Partly | I29: Price x SEC share count. Unreliable for ADRs (ADR ratio unknown), multi-class shares or missing share counts -> 'check manually' (~150 ADRs last run).
A30: Emerging Compounders | B30: E13 | C30: Liquidity | D30: Avg daily value traded >= $200k | E30: Tradeability | F30: Connor Haley states that trading of at least $200k a day means a stock is "reasonably liquid" for a small and micro cap investor, because a fund has to be able to build and exit a real position. A mentioned example: Alta Fox's 104-multibagger study used average daily value traded over $200k as an entry filter. | G30: Tradeable. | H30: Easy
A31: Emerging Compounders | B31: J | C31: Human / AI review | D31: Why overlooked, niche dominance, customer concentration (~70% = kill), insider stake >= 5%, acquisition-led growth | E31: Judgment | F31: Connor Haley states that the questions numbers miss decide the case, because "why might this stock be mispriced" is the key question, 70% customer concentration is a risk that never goes away, and small-cap managers should own at least about 5%. A mentioned example: XPEL, a focused niche leader that competes with far bigger 3M, which he says a focused player can often out-innovate. Pat Dorsey states that moat strength needs human research, because "you can't screen for switching costs"; you have to talk to customers and others who know the business. No specific past example given. | G31: Decides whether the numbers reflect a real thesis. | H31: No | I31: Qualitative; not in financial data. Left to the AI review + you.
A32: Special Situations | B32: U | C32: Universe (event) | D32: Spin-off (Form 10), bankruptcy (8-K item 1.03) or IPO (S-1/F-1) in last 36 months; no funds/banks/insurers | E32: Trigger | F32: Joel Greenblatt states that spin-offs and post-bankruptcy stocks mean likely mispricing, because analysts stop covering a messy company "until the smoke is cleared", and lenders handed shares in a bankruptcy usually sell them. A mentioned example: his Sears stub, bought for about $5 in 1993, reached $30 in two months. Connor Haley states that spin-offs, post-bankruptcy firms and recent IPOs mean a possible edge, because the market has not had long to analyze them, so they can stay mispriced. No specific past example given. | G32: The source of the edge. | H32: Partly | I32: Spin-offs without a Form 10 (e.g. foreign) can be missed; 8-K 1.03 dates the filing, not the emergence.
A33: Special Situations | B33: S1 | C33: Recent report | D33: Last annual report <= 1.6 years old | E33: Data | F33: No investor source: a data-quality rule, because you need current filed numbers to judge the business. | G33: Keeps the screen current. | H33: Partly | I33: New listings often have no annual report yet (only Form 10/prospectus) -> no data.
A34: Special Situations | B34: S2 | C34: Profitable business | D34: TTM operating income > 0 | E34: Quality | F34: Joel Greenblatt states that real operating profit means you can judge whether the business is both good and cheap, because he measures stocks on EBIT against enterprise value and against capital, looking for high returns bought at a high earnings yield. A mentioned example: NII Holdings, a post-bankruptcy wireless business at 2.8x EBITDA, went from $10 to $240 split-adjusted. | G34: Avoids broken companies. | H34: Partly | I34: New listings often lack tagged history -> no data.
A35: Special Situations | B35: S3 | C35: Leverage | D35: Net debt / EBITDA <= 4x | E35: Safety | F35: Brian Gaines states that heavy debt turns the equity into "an option bet", because the capital structure decides whether a company can be pushed into bankruptcy: banks can force it, while fixed-rate bondholders cannot. A mentioned example: Movie Gallery, with $1.1 billion of debt on about 30 million shares, which he said had become an option bet whose share price meant little. | G35: Equity isn't an option bet. | H35: Easy | I35: Rare: debt in non-standard tags or D&A untagged -> flagged.
A36: Special Situations | B36: S4 | C36: Cheap | D36: EV / EBIT <= 15x | E36: Valuation | F36: Joel Greenblatt states that a low EV/EBIT means you are paid well for the risk, because he thinks in pre-tax multiples against a bond yield of at least 6%: about 10x EBIT is similar to that yield, and 12x needs real certainty. A mentioned example: he warned students who put 12x EBIT on their write-ups that only a pretty good business deserves it. | G36: Margin of safety on the mispricing. | H36: Partly | I36: Price x SEC share count. Unreliable for ADRs (ADR ratio unknown), multi-class shares or missing share counts -> 'check manually' (~150 ADRs last run). New listings may lack a share count.
A37: Special Situations | B37: S5 | C37: Size (market cap) | D37: Market cap >= $100M | E37: Tradeability | F37: No investor source: a tradeability rule, because very small companies are hard to buy without moving the price. | G37: Tradeable size. | H37: Partly | I37: Price x SEC share count. Unreliable for ADRs (ADR ratio unknown), multi-class shares or missing share counts -> 'check manually' (~150 ADRs last run).
A38: Special Situations | B38: S6 | C38: Liquidity | D38: Avg daily value traded >= $200k | E38: Tradeability | F38: No investor source: a tradeability rule, because you must be able to get in and out of the stock. | G38: Tradeable. | H38: Easy
A39: Special Situations | B39: J | C39: Human / AI review | D39: Why the parent spins it off, who must sell, management incentives, debt loaded on the spinco, hidden assets | E39: Judgment | F39: Joel Greenblatt states that you must read why the parent is acting and how managers are paid, because many spin-offs come from a position of weakness, and stock owned versus yearly pay is the main thing he checks on management. A mentioned example: when Sears said it had no intention of disposing of Allstate, he read it as a sign it would. Brian Gaines states that insiders putting more money in means the business is not falling apart, because they know more than outsiders do. A mentioned example: Hollywood Video's CEO Mark Wattles rolled his stake into a buyout, going from about 10% to 50% ownership. Chris Davis states that hidden assets and senior claims change the real price, because you should value the whole company like a buyer, counting debt and pensions and assets carried below value. No specific past example given. | G39: Decides whether the numbers reflect a real thesis. | H39: No | I39: Needs reading the Form 10 / reorganization plan.
A40: Fortress | B40: U | C40: Universe | D40: Same as Core | E40: Universe | F40: Chris Hohn states that leaving out banks, airlines, wireless telecom, media and ad agencies means avoiding what he calls bad businesses, because they face heavy competition or, for banks, high leverage, so profits are fragile. A mentioned example: air travel grew about 5% a year for a century, yet airlines collectively made minimal profits. Pat Dorsey states that excluding industries like airlines, auto parts, life insurance and oil and gas means avoiding price takers, because a large part of their future is not under their control. No specific past example given. Terry Smith states that dropping low-return sectors makes sense because good-company sectors don't become bad ones and vice versa; low-return industries stay low. A mentioned example: the airline industry, which he says never makes an adequate return on capital. | G40: Same as Core. | H40: Easy | I40: Uses SEC industry (SIC) code; codes can be coarse or outdated (manual override list exists).
A41: Fortress | B41: F1 | C41: History | D41: >= 9 years of data | E41: Data | F41: Stanley Druckenmiller states that a record spanning a recession matters, because how earnings behave in a downturn shows whether they are sustainable, and sustainable recession earnings protect the stock. No specific past example given. Dev Kantesaria states that a long record matters because he only owns companies he is confident stay dominant for at least 10 years, preferring business models that have already worked for decades. No specific past example given. | G41: Lets the recession tests run. | H41: Easy
A42: Fortress | B42: F2 | C42: Recent report | D42: Last annual report <= 1.6 years old | E42: Data | F42: No investor source: old financial statements can hide a recent collapse, so the latest annual report must be current. | G42: Keeps the screen current. | H42: Easy | I42: Rare: some foreign (20-F) reports filed but not yet in SEC XBRL data -> flagged.
A43: Fortress | B43: F3 | C43: Size (revenue) | D43: Revenue >= $500M | E43: Size | F43: No investor source: very small filers have patchier data and are harder to own in meaningful size. | G43: Focus on established businesses. | H43: Easy
A44: Fortress | B44: F4 | C44: Held up in 2020 | D44: 2020 revenue >= -5% and operating income >= -15% | E44: Safety | F44: Stanley Druckenmiller states that profits holding up in a recession mean the stock is protected, because "if you have very good earnings in a recession and they're sustainable" the market eventually sees it. A mentioned example: in June 2023 he argued that if staples can rise in a recession, Nvidia could too, with orders and earnings up about 70% in a hard landing. | G44: Recession-proof earnings (the thesis). | H44: Easy
A45: Fortress | B45: F5 | C45: Held up in 2009 | D45: 2009 revenue >= -10%, operating income >= -25%; recession loss fails | E45: Safety | F45: Stanley Druckenmiller states that holding up in a deep recession signals resilient earnings, because a hard landing normally hits profits hard and only sustainable earnings protect the stock. A mentioned example: his May 2023 hard-landing template had corporate profits falling "20 percent plus" and unemployment rising from 3.4% to above 5%. | G45: Second proof of resilience. | H45: Partly | I45: SEC XBRL data mostly starts 2009-11 -> 2008-09 missing for many (~35 flagged); check old annual reports.
A46: Fortress | B46: F6 | C46: Never lost money | D46: 0 operating-loss years | E46: Quality | F46: Dev Kantesaria states that never losing money signals the predictability he insists on, because he hates to lose a single dollar and avoids anything that "could go down 90% tomorrow", preferring business models that have succeeded for decades. No specific past example given. | G46: Predictability. | H46: Easy
A47: Fortress | B47: F7 | C47: Stable margins | D47: Operating margin std. dev. <= 5 pts (10 yrs) | E47: Quality | F47: Dev Kantesaria states that stable results signal predictable earnings, which he values so highly that he is "happy to give up some growth in exchange for predictability", because predictability gives a margin of safety if his assumptions are wrong. A mentioned example: Nestlé and Hershey, which he calls extremely predictable (though too slow-growing). | G47: Low earnings volatility. | H47: Easy
A48: Fortress | B48: F8 | C48: Decent returns | D48: 10-yr median ROIC >= 10% | E48: Quality | F48: Chris Hohn states that some capital-heavy assets still have strong moats, because airports, toll roads, railroads and telecom towers are natural monopolies that are hard to compete with, and parts of their income need little capital. A mentioned example: Spain's privatized airport group Aena; "they'll never build a second airport at Madrid". Dev Kantesaria states that toll collectors on essential activity are great businesses, because they can keep raising the toll even when volume dips. A mentioned example: Moody's and S&P Global, which he describes as toll collectors. | G48: Quality floor. | H48: Easy | I48: Rare: debt in non-standard tags or D&A untagged -> flagged.
A49: Fortress | B49: F9 | C49: Leverage | D49: Net debt / EBITDA <= 2x | E49: Safety | F49: Paul Singer states that surviving comes first, because big losses wreck judgment while intact capital lets you act in a crisis: "you make a buck you keep it". A mentioned example: he lost 88% of his parents' money on margin in 1974; in late 2008 "everything got cheap" for those with capital left. Sander Gerber states that heavy leverage is dangerous when rates stay high, because borrowers won't be able to refinance at the same rate or make their debt payments, so leveraged structures break down. No specific past example given. | G49: Downside protection. | H49: Easy | I49: Rare: debt in non-standard tags or D&A untagged -> flagged.
A50: Fortress | B50: F10 | C50: Interest coverage | D50: EBIT / interest >= 6x | E50: Safety | F50: Stanley Druckenmiller states that cheap debt locked in earlier will reprice, because corporations "termed out their debt" and "that stuff rolls over in 25 and 26", so interest costs rise to today's rates. A mentioned example: in COVID, 80% of individuals refinanced mortgages, keeping the average rate under 4% though new mortgages reached 8% (Nov 2024). | G50: Refinancing safety. | H50: Easy | I50: If interest isn't tagged, a worst-case estimate is used.
A51: Fortress | B51: F11 | C51: Refinancing | D51: Debt due in 2 yrs <= cash + 2 yrs of FCF | E51: Safety | F51: Matt Mark states that debt coming due can cause a crisis even when assets cover it, because bondholders want their money at maturity, not promised future asset sales. A mentioned example: Grupo TMM had about $400M of debt against a roughly $470M asset sale, yet with notes due in 2003 it sought a Mexican court order against default claims, and its bonds fell to about 60 cents. Sander Gerber states that maturities are the danger point when rates stay high, because borrowers won't be able to refinance at the same rate or make their payments. No specific past example given. | G51: No liquidity squeeze. | H51: Partly | I51: Maturity schedule often not tagged (e.g. LMT, KMB) -> check the debt note.
A52: Fortress | B52: F12 | C52: Cash every year | D52: <= 1 negative-FCF year | E52: Quality | F52: Peter Thiel states that cash piling up year after year is the financial signature of a monopoly-like business, because such companies keep very high profit margins with little competition. A mentioned example: Apple, Google, Microsoft and Amazon, which he says have built up cash year after year. Terry Smith states that cash is the true test of quality, because he measures returns as cash delivered in a period divided by capital employed, not reported profit. No specific past example given. | G52: Resilient cash flow. | H52: Easy | I52: Rare: capex not in a standard tag -> estimated or flagged.
A53: Fortress | B53: F13 | C53: Inflation test | D53: Gross margin change 2021-23 >= -2 pts | E53: Quality | F53: Chris Hohn states that pricing above inflation is the test of a moat, because most companies can only price at inflation if lucky, while a 1% real price rise at a 20% margin grows profits about 5% faster than revenue. No specific past example given. Dev Kantesaria states that pricing power is the best protection from inflation, because an essential product can raise prices a few percent above inflation for a decade or more, compounding intrinsic value. No specific past example given. | G53: Pricing-power evidence. | H53: Easy
A54: Fortress | B54: Flag | C54: Margin collapse / revenue shrinking | D54: As in Core | E54: Warning | F54: Chris Hohn states that falling profits can mean competition is breaking in, because too much competition erodes profits until you may make no money at all. No specific past example given. Terry Smith states that shrinking revenue must be judged across the cycle, because a secular grower's peaks and troughs should each be bigger than the last. No specific past example given. | G54: Early warning. | H54: No | I54: Detected automatically; temporary vs permanent needs a human.
A55: Fortress | B55: V | C55: Valuation | D55: None (price-blind by design) | E55: Valuation | F55: Dev Kantesaria states that price should not decide inclusion, because whether a P/E is 24, 28 or 32 matters far less than picking the right companies, and value growth overcomes overpaying by 10 or 15%. No specific past example given. Terry Smith states that business quality matters more than price, because over a long hold your return converges on the business's return on capital. A mentioned example: Munger's point that a business earning 6% for 40 years returns about 6% even if bought at a huge discount. | G55: - | H55: n/a | I55: No 'cheap enough' test - see Valuation sheet.
A56: Fortress | B56: J | C56: Human / AI review | D56: Is resilience structural (essential, recurring)? Contract durability, regulation, what would break it | E56: Judgment | F56: Chris Hohn states that resilience needs judgment on whether the need is essential and the barriers durable, because most of a company's value lies 20-30 years out; barriers too low invite competition, too high invite regulators. A mentioned example: airports, where landing charges are regulated but shops, parking and lounges are not. Pat Dorsey states that contract and customer durability can't be read from numbers, because "you can't screen for switching costs"; it takes talking to customers and ex-employees. No specific past example given. | G56: Decides whether the numbers reflect a real thesis. | H56: No | I56: Qualitative; not in financial data. Left to the AI review + you.
A57: Healthcare - Commercial | B57: U | C57: Universe | D57: Healthcare SIC codes: pharma, devices, tools, distribution, insurers, services | E57: Universe | F57: Terry Smith states that commercial pharma and health care companies belong in a quality screen, because these sectors keep earning high returns on capital over decades instead of fading to average. A mentioned example: his sector chart shows pharmaceuticals and health care with high returns both in 1963–2004 and in the latest 20 years. Connor Haley states that healthcare needs its own rules, because government regulation "greatly impacts the healthcare space", so some winners enjoy conditions that may not last. A mentioned example: healthcare did surprisingly well in Alta Fox's 2015–20 multibagger study, but he said its top winner, Zynex, may have benefited from dynamics that may not persist. | G57: Like-for-like comparison. | H57: Easy | I57: Uses SEC industry (SIC) code; codes can be coarse or outdated (manual override list exists).
A58: Healthcare - Commercial | B58: H1 | C58: History | D58: >= 5 years of data | E58: Data | F58: Terry Smith states that a long record shows whether a company is truly good, because returns persist for decades: "Good companies don't become bad companies by and large or vice versa." A mentioned example: in ROE data going back to 1966, high-return companies stayed near 20% and low-return ones near 12%. | G58: Makes return and stability numbers meaningful. | H58: Easy
A59: Healthcare - Commercial | B59: H2 | C59: Recent report | D59: Last annual report <= 1.6 years old | E59: Data | F59: No investor source: an old annual report can hide a recent collapse, so the latest numbers must be reasonably current. | G59: Keeps the screen current. | H59: Easy | I59: Rare: some foreign (20-F) reports filed but not yet in SEC XBRL data -> flagged.
A60: Healthcare - Commercial | B60: H3 | C60: Size (revenue) | D60: Revenue >= $200M | E60: Size | F60: No investor source: very small filers have patchier data and are hard to buy in a useful size. | G60: Focus on established businesses. | H60: Easy
A61: Healthcare - Commercial | B61: H4 | C61: Consistent profits | D61: <= 1 loss year in last 5 | E61: Quality | F61: Connor Haley states that steady profits mark a proven business rather than a cash burner, because a company already making money does not need to keep raising cash and diluting owners. A mentioned example: in Alta Fox's study of 104 multibaggers (2015–20), most were profitable five years earlier, "relatively proven concepts" that "weren't losing millions". | G61: Predictability. | H61: Easy
A62: Healthcare - Commercial | B62: H5 | C62: High returns | D62: 10-yr median ROIC >= 12% | E62: Quality | F62: Terry Smith states that a high return on capital marks a quality business, because return on capital is "the single most important thing" and high returns persist for decades. A mentioned example: pharmaceuticals and health care are among the sectors with high returns on capital in both 1963–2004 and the latest 20 years. Joel Greenblatt states that a pre-tax return of 14% is generally not good, while 20% pre-tax, about 12% after a 40% tax, is decent though not amazing, because it leaves room for error. No specific past example given. | G62: Moat evidence (patents, installed base). | H62: Easy | I62: Rare: debt in non-standard tags or D&A untagged -> flagged.
A63: Healthcare - Commercial | B63: H6 | C63: Gross margin (products) | D63: Gross margin >= 50% | E63: Quality | F63: Bihua Chen states that a high gross margin is what a real drug business looks like, because a pharmaceutical company's gross margin should be 80 to 90%, with operating margin up to about 50% depending on marketing costs and efficiency. No specific past example given. | G63: Pricing power. | H63: Easy | I63: Rare: no gross-profit line (e.g. REGN) -> no data.
A64: Healthcare - Commercial | B64: H7 | C64: Cash conversion | D64: FCF / net income >= 0.7 | E64: Quality | F64: Terry Smith states that turning profits into cash shows the returns are real, because he measures return on capital as cash delivered against the capital employed. A mentioned example: the MSCI World quality subset (high returns on capital, high margins, good cash conversion) beat the index in every rolling 10-year period since 1996. Connor Haley states that free cash flow is the number to trust, because earnings and EBITDA, unlike free cash flow, "can be easily manipulated". No specific past example given. | G64: Earnings quality. | H64: Easy | I64: Rare: capex not in a standard tag -> estimated or flagged.
A65: Healthcare - Commercial | B65: H8 | C65: Leverage | D65: Net debt / EBITDA <= 3x | E65: Safety | F65: Connor Haley states that debt taken on to buy another business makes a company fragile, because a sudden shock can leave it short of cash and facing bankruptcy. A mentioned example: Alta Fox sold a well-run restaurant stock that had just levered up for an acquisition right before COVID; it survived, but he defends the sale. Brian Gaines states that heavy debt turns the shares into an option bet, because banks can force a bankruptcy in a bad patch, so share-price moves say little about the company's value. A mentioned example: Movie Gallery, with $1.1 billion of debt and about 30 million shares, fell to $6.80 by late 2005. | G65: Downside protection. | H65: Easy | I65: Rare: debt in non-standard tags or D&A untagged -> flagged.
A66: Healthcare - Commercial | B66: H9 | C66: Growing | D66: Revenue CAGR >= 3% | E66: Growth | F66: Terry Smith states that growing sales show a company can reinvest its high returns, because high returns are wasted in a business that can't grow; he wants secular growth, where each cycle's peak and trough beat the last. No specific past example given. Jim Flynn states that shrinking sales at a drug company can mean a patent has expired, because "a generic will get 98% of volume within a month" after a patent ends, so branded revenue is close to all-or-nothing. No specific past example given. | G66: Franchise still growing. | H66: Easy
A67: Healthcare - Commercial | B67: Flag | C67: Margin collapse / revenue shrinking | D67: As in Core | E67: Warning | F67: Dave Johnson states that falling revenue at a drug company can signal a patent cliff, because after a typical patent cliff revenues fall about 90%. A mentioned example: Incyte's blockbuster Jakafi goes off patent in 2028 with nothing in Incyte's portfolio to replace it (Jun 2023). Jim Flynn states that growth from price rises in old drug classes is at risk of a forced price cut, because lawmakers target classes where prices rise despite competition. A mentioned example: TNF-inhibitor prices "inch up not down" despite many rivals, and Congress was discussing legislating competition into such classes (Nov 2021). | G67: Early warning. | H67: No | I67: Detected automatically; temporary vs permanent needs a human.
A68: Healthcare - Commercial | B68: V | C68: Valuation | D68: None (price-blind by design) | E68: Valuation | F68: Terry Smith states that the first question is how good the business is, because a low price can't make a bad company good: "It may give you a short-term opportunity, but it certainly doesn't give you a long-term one." A mentioned example: low-return sectors such as utilities, telecoms, transport and retailing stayed low for decades. Chris Davis states that business quality outweighs entry price for a long-term owner, because "your return over time is going to approach the return on equity of the business, no matter what your starting price is." No specific past example given. | G68: - | H68: n/a | I68: No 'cheap enough' test - see Valuation sheet.
A69: Healthcare - Commercial | B69: J | C69: Human / AI review | D69: Patent expiries next 5 yrs (% revenue), Medicare/Medicaid share, price-led growth, pipeline depth | E69: Judgment | F69: Joel Greenblatt states that heavy reliance on Medicare or Medicaid caps returns, because if such companies make too much money for a while "they change the rules" and pay less, so never assume outlandish returns. A mentioned example: for-profit hospitals, which can still earn decent returns by running more efficiently on the same Medicare rates. Dave Johnson states that revenue from drugs nearing patent expiry is at risk, because revenue typically falls about 90% after the cliff, while trade-secret products can avoid it. A mentioned example: Botox has no generic after 20+ years because its cell bank is a trade secret nobody can copy. Jim Flynn states that a product's future depends on what could replace it, because the biggest public-market question is when a company's product becomes obsolete and "What's coming behind it", which Deerfield's private-side view helps answer. No specific past example given. | G69: Decides whether the numbers reflect a real thesis. | H69: No | I69: Not in financial data; AI review + 10-K reading.
A70: Healthcare - Clinical | B70: U | C70: Universe | D70: Pharma/biotech/device SIC codes, not commercial-stage (revenue < $200M or operating loss) | E70: Universe | F70: Bihua Chen states that a pre-revenue biotech can't be judged on earnings, because its value turns on whether the drug works; projecting cash flows and comparing peers is the "less value added" part. A mentioned example: an Alzheimer's antibiotic theory built on a correlation failed an adequately sized placebo-controlled trial. Connor Haley states that requiring positive trailing EBITDA removes biotech from a generalist screen, because such companies "aren't in sort of the generalist investor framework". A mentioned example: Alta Fox's 2020 multibagger study used exactly this filter to take biotech out. | G70: Separate 'cash floor + option' logic. | H70: Easy | I70: Uses SEC industry (SIC) code; codes can be coarse or outdated (manual override list exists).
A71: Healthcare - Clinical | B71: B1 | C71: Recent balance sheet | D71: Balance sheet <= 200 days old | E71: Data | F71: No investor source: clinical companies burn cash quickly, so the cash figure is only useful if the balance sheet is recent. | G71: Accurate floor. | H71: Easy
A72: Healthcare - Clinical | B72: B2 | C72: Cash runway | D72: Cash / annual burn >= 2 yrs | E72: Safety | F72: Bihua Chen states that cash burn makes biotech prices depend on financing, because biotechs are long-dated assets that "burn a lot of money" under "a lot of financing pressure", so she passes when there isn't enough capital to reach the next proof point. No specific past example given. Jim Flynn states that cash-hungry biotechs listed in a bubble tend not to last, because bubbles let in companies that are "too early, too risky, require too much cash", and they "just have to go away". A mentioned example: in May 2025 biotech had just been through his third bubble and collapse in 36 years. Eli Casdin states that a long cash runway keeps a company from failing for lack of money, because he is "over capitalizing these businesses so they're not going to run out of money", scaling up his investment over time instead of putting everything in first and fighting dilution on the way down. A mentioned example: his companies burn about $100–150 million every 12–24 months (2022). | G72: Time to reach the next catalyst. | H72: Easy | I72: Burn = last 12 months operating cash flow.
A73: Healthcare - Clinical | B73: B3 | C73: Little debt | D73: Debt / cash <= 0.5 | E73: Safety | F73: Dave Johnson states that a convertible bond ahead of shareholders weighs on the stock, because it is a claim on the company's cash. A mentioned example: MorphoSys's convertible traded at a big discount, and within about six weeks of Caligan's push the company bought back about 25% of it (2023). Jim Flynn states that senior secured debt comes ahead of shareholders, because the lender's part "protects your basis" and lets the lender take control if the company fails. A mentioned example: when COVID nearly sank Melinta, Deerfield, as secured lender, credit-bid, took over the company and later sold it for over $300 million. | G73: Floor belongs to shareholders. | H73: Easy
A74: Healthcare - Clinical | B74: B4 | C74: Size (market cap) | D74: Market cap >= $50M | E74: Tradeability | F74: No investor source: below about $50M of market value a stock is hard to buy without moving the price. | G74: Tradeable size. | H74: Partly | I74: Price x SEC share count. Unreliable for ADRs (ADR ratio unknown), multi-class shares or missing share counts -> 'check manually' (~150 ADRs last run).
A75: Healthcare - Clinical | B75: B5 | C75: Liquidity | D75: Avg daily value traded >= $200k | E75: Tradeability | F75: Connor Haley states that a minimum daily trading value makes a stock practical to own, because a fund needs enough trading to build and exit a position. A mentioned example: Alta Fox's multibagger study required average daily value traded over $200,000, "reasonably liquid" for a small and micro cap investor. | G75: Tradeable. | H75: Easy
A76: Healthcare - Clinical | B76: B6 | C76: Floor value | D76: EV / cash <= 0.25 | E76: Valuation | F76: Dave Johnson states that an enterprise value near or below cash means you get the drug pipeline almost free, because cash and approved assets already cover the price. A mentioned example: MorphoSys had negative EV from December 2022 with about €1 billion of cash: "you own this option for nothing". Joel Greenblatt states that a stock priced at its cash, with a business not burning money, comes almost free, because management has no incentive to waste the cash and the business may turn into something: "almost like a free option". No specific past example given. | G76: Hard downside floor + free upside. | H76: Partly | I76: Price x SEC share count. Unreliable for ADRs (ADR ratio unknown), multi-class shares or missing share counts -> 'check manually' (~150 ADRs last run).
A77: Healthcare - Clinical | B77: J | C77: Human / AI review | D77: Lead asset and phase, next catalyst and date, science quality, crowded mechanism, management record | E77: Judgment | F77: Dave Johnson states that the lead drug's stage decides the risk, because Caligan avoids scientific risk by investing mostly at Phase 3 or later, and stocks sit in a "catalyst desert" between readouts. A mentioned example: MorphoSys's Phase 3 pelabresib, valued at up to about 45 per share against under 13 paid (Jun 2023). Bihua Chen states that science quality and crowding need expert judgment, because "Every company will tell you something is causal, and most time it's not", and once a pathway works about 20 companies can flood in. A mentioned example: the Alzheimer's antibiotic theory that failed its placebo-controlled trial. Eli Casdin states that management quality needs a human test, because, as he puts it, "A's hire A+ people" while B's hire C's, so thinning talent down the ranks is a warning sign. A mentioned example: he suggests an improvement; a team that calls it a good idea is a red flag, while one that started it months ago reassures. | G77: Decides whether the numbers reflect a real thesis. | H77: No | I77: Numbers can't judge science; AI review reads the pipeline.
A78: Cyclicals | B78: U | C78: Universe | D78: Capacity-cycle industries: metals, energy, chemicals, building materials, homebuilders, machinery, semis, autos, transport | E78: Universe | F78: Stanley Druckenmiller states that capacity-cycle industries need cycle-aware rules, because when companies lose money capacity shrinks and margins recover within about three years, while flush industries announce expansions that bring margins down. A mentioned example: chemicals, his early sector, where you bought when everyone was losing money and shutting capacity. Connor Haley states that a cyclical company must be judged on trough numbers, because its profits swing with the cycle, so he wants it at a trough multiple on trough margins. No specific past example given. | G78: Right yardstick for cyclicals. | H78: Easy | I78: Uses SEC industry (SIC) code; codes can be coarse or outdated (manual override list exists).
A79: Cyclicals | B79: C1 | C79: History | D79: >= 8 years of data | E79: Data | F79: Joel Greenblatt states that a long record means you can see the bad years and find normal earnings, because good and bad years must be averaged: $10 a year for nine years plus one break-even year is about $9. A mentioned example: Wells Fargo could earn about $18 a share in a normal year yet roughly zero once every seven or eight years. | G79: Enables cycle-average figures. | H79: Easy
A80: Cyclicals | B80: C2 | C80: Recent report | D80: Last annual report <= 1.6 years old | E80: Data | F80: No investor source: a data-quality rule, because old annual numbers can hide a recent collapse. | G80: Keeps the screen current. | H80: Easy | I80: Rare: some foreign (20-F) reports filed but not yet in SEC XBRL data -> flagged.
A81: Cyclicals | B81: C3 | C81: Size (revenue) | D81: Revenue >= $200M | E81: Size | F81: No investor source: a data and ownership rule, because tiny filers have patchier numbers and are hard to own. | G81: Focus on established businesses. | H81: Easy
A82: Cyclicals | B82: C4 | C82: Mid-cycle returns | D82: 10-yr median ROIC >= 10% | E82: Quality | F82: Chris Davis states that solid returns on capital mean the business, not the entry price, drives a long-term owner's return, because "your return over time is going to approach the return on equity of the business, no matter what your starting price is." A mentioned example: buy a business at half of book that keeps reinvesting at 4%, and your return heads toward 4%. Terry Smith states that a good return record means a good business, because returns on capital stay persistent for decades and a low rating does not turn a bad company into a good one. A mentioned example: in his sector data, transport, energy and materials stayed persistently low-return groups. | G82: Quality filter. | H82: Easy | I82: Rare: debt in non-standard tags or D&A untagged -> flagged.
A83: Cyclicals | B83: C5 | C83: Survives downturns | D83: >= 7 profitable (EBIT) years | E83: Quality | F83: Joel Greenblatt states that staying profitable in bad years means a cyclical is worth more than its swings suggest, because a business that does not lose money in a bust keeps its earning power and survives. A mentioned example: NVR, a homebuilder with pre-sold homes and little capital tied up, which in a downturn might take a small hit but probably would not lose money. | G83: Survival. | H83: Easy
A84: Cyclicals | B84: C6 | C84: Leverage | D84: Net debt / avg EBITDA (cycle) <= 2.5x | E84: Safety | F84: Joel Greenblatt states that low debt matters most in cyclicals, because whether a company survives the cycle depends on how leveraged it is, and you don't want to lever up a very cyclical business. No specific past example given. Brian Gaines states that heavy debt turns the equity into "an option bet", because banks can force a levered company into bankruptcy in a bad stretch. A mentioned example: Movie Gallery, with $1.1 billion of debt on about 30 million shares. Connor Haley states that a strong balance sheet means downside protection, because it lets a company survive a shock. A mentioned example: in March 2020 Alta Fox sold a restaurant stock that had just borrowed for an acquisition before COVID. | G84: Survives the next downturn. | H84: Easy | I84: Rare: debt in non-standard tags or D&A untagged -> flagged.
A85: Cyclicals | B85: C7 | C85: Not at peak margins | D85: Latest margin in lower half of own 10-yr range | E85: Trigger | F85: Stanley Druckenmiller states that buying when margins are low means buying before the recovery, because "when companies are losing money, capacity is always going to shrink and their margins going to look better in 3 years", while over-earners' margins come down. A mentioned example: in 2022 he named ocean shipping, with "massive margins", among the true over-earners, after retail and trucking. Connor Haley states that a cyclical should be bought at trough margins, because buying near peak margins means buying profits that will shrink. No specific past example given. | G85: Cycle timing (core of the thesis). | H85: Easy | I85: Own history only; industry capacity cycle isn't measured.
A86: Cyclicals | B86: C8 | C86: Cheap on normalized earnings | D86: EV / 10-yr avg EBIT <= 12x | E86: Valuation | F86: Joel Greenblatt states that a low price on cycle-average earnings means a real bargain, because he draws the normal earnings line through good and bad years and pays a low multiple on it, instead of trusting one year. A mentioned example: Wells Fargo, with normalized earnings near $16 a share at about $70, dipped to $60 and later reached $250. Connor Haley states that a cyclical should trade at a trough multiple on trough margins, because then the price already assumes the bad part of the cycle. No specific past example given. | G86: Margin of safety if the cycle turns slowly. | H86: Partly | I86: Price x SEC share count. Unreliable for ADRs (ADR ratio unknown), multi-class shares or missing share counts -> 'check manually' (~150 ADRs last run).
A87: Cyclicals | B87: J | C87: Human / AI review | D87: Industry capacity (closures vs expansions), cyclical vs structural margin drop | E87: Judgment | F87: Stanley Druckenmiller states that the capacity picture tells you where margins go next, because industries shutting capacity recover while flush ones announcing expansions show you what is coming. A mentioned example: in chemicals, companies used to announce capacity expansions at the peak, "so you knew what was going to happen." Joel Greenblatt states that the key question for a cheap, troubled stock is whether its problem is temporary or permanent, because only a temporary problem makes the low price a bargain. A mentioned example: Rich Pzena's case for Lear, the auto supplier, rested on showing its problem was short-term. | G87: Decides whether the numbers reflect a real thesis. | H87: No | I87: Industry capacity data isn't in SEC filings.
A88: Owner-Operators | B88: U | C88: Universe | D88: Same as Core | E88: Universe | F88: Terry Smith states that leaving out utilities, telecoms, transport, energy, materials and retailing means skipping businesses whose returns stay low, because returns on capital persist for decades and being cheap doesn't turn a bad company into a good one. A mentioned example: airlines, which he says never make an adequate return on capital. Chris Hohn states that avoiding banks, autos, retail, insurance, commodities, airlines, telecoms and media means skipping businesses without real barriers to entry, because growth without barriers earns little for owners. A mentioned example: airlines grew about 5% a year for a century with minimal profit. | G88: Same as Core. | H88: Easy | I88: Uses SEC industry (SIC) code; codes can be coarse or outdated (manual override list exists).
A89: Owner-Operators | B89: O1 | C89: History | D89: >= 5 years of data | E89: Data | F89: Terry Smith states that a long record of returns means you can tell a truly good company from a lucky one, because high and low returns on capital tend to persist for decades. A mentioned example: return-on-equity data back to 1966, where the high-return group kept clustering around 20% and stayed well above the low group. Joel Greenblatt states that one year of high returns proves little, because last year's return on capital may be a cyclical peak or include one-off items, so it may not be the return going forward. No specific past example given. | G89: Makes return and stability numbers meaningful. | H89: Easy
A90: Owner-Operators | B90: O2 | C90: Recent report | D90: Last annual report <= 1.6 years old | E90: Data | F90: No investor source: old filings can hide a recent collapse, so the screen only uses companies with a fresh annual report. | G90: Keeps the screen current. | H90: Easy | I90: Rare: some foreign (20-F) reports filed but not yet in SEC XBRL data -> flagged.
A91: Owner-Operators | B91: O3 | C91: Size (revenue) | D91: Revenue >= $50M | E91: Size | F91: No investor source: very small filers have patchy data and are hard to own in a meaningful size. | G91: Focus on established businesses. | H91: Easy
A92: Owner-Operators | B92: O4 | C92: Insider ownership | D92: Insider share >= 20% | E92: Trigger | F92: Murray Stahl states that high insider ownership means an owner-operator, someone who runs the company because they own more of it than anyone else, because their wealth moves with the shares; float-weighted indexes also underweight such firms, leaving them cheaper. A mentioned example: his S&P 500 study back to 1957, where owner-operators earned the bulk of the return. Chris Davis states that managers who are real owners means incentives are aligned with shareholders, because managers who aren't owners chase the most pay possible, which is an expense for owners; "We want to invest in owner-operators." No specific past example given. Connor Haley states that management owning at least about 5% in small and micro caps means they care about shareholders, because their own net worth rises and falls with the stock. A mentioned example: XPEL's CEO Ryan Pape keeps a material part of his net worth in the stock and, Haley believes, has never sold a share. | G92: Alignment + under-owned by index funds (cheaper). | H92: Partly | I92: From cover-page public float. Foreign filers report none (~43); no share count near float date (~29); share-class mismatches.
A93: Owner-Operators | B93: O5 | C93: Consistent profits | D93: <= 2 operating-loss years | E93: Quality | F93: Connor Haley states that a record of profits means a proven business rather than a cash burner, because companies already making money don't need to dilute shareholders to survive and can grow into operating leverage. A mentioned example: Alta Fox's study of 104 multibaggers from 2015-20, most of which were already profitable five years before their big run. Joel Greenblatt states that a single bad year should not disqualify a steady business, because what matters is normalized earnings across years: a company earning $10 for nine years and breaking even in one is worth roughly $9 of normal earnings. No specific past example given. | G93: Quality floor. | H93: Easy
A94: Owner-Operators | B94: O6 | C94: High returns | D94: 10-yr median ROIC >= 12% | E94: Quality | F94: Terry Smith states that a high return on capital means a business can compound in value, because over a long holding your return converges on what the business earns on its capital; he calls return on capital "the single most important thing". A mentioned example: airlines, which he says never make an adequate return on capital. Joel Greenblatt states that a high return on tangible capital means a good business, because it shows the profit on each dollar tied up in the business: pre-tax 14% is generally not good, while 20% (about 12% after tax) is decent. A mentioned example: Moody's, which needed no reinvestment and was the best business he had ever found. | G94: Compounding engine. | H94: Easy | I94: Rare: debt in non-standard tags or D&A untagged -> flagged.
A95: Owner-Operators | B95: O7 | C95: Cash conversion | D95: FCF / net income >= 0.6 | E95: Quality | F95: Connor Haley states that relying on free cash flow means trusting the number hardest to fake, because earnings and EBITDA "can be easily manipulated". No specific past example given. Terry Smith states that good cash conversion is a mark of quality, because profits only count if they arrive as cash, so he measures return on capital in cash. A mentioned example: the MSCI World quality subset (high returns, high margins, good cash conversion) beat the index in every rolling 10-year period since 1996. Dan Sundheim states that profits that don't reconcile with the cash and unit economics can signal accounting abuse, because capitalizing costs that should be expensed lifts profit without bringing in cash. A mentioned example: Orthodontic Centers of America, where he found "the simplest form of accounting fraud". | G95: Earnings quality. | H95: Easy | I95: Rare: capex not in a standard tag -> estimated or flagged.
A96: Owner-Operators | B96: O8 | C96: Leverage | D96: Net debt / EBITDA <= 2.5x | E96: Safety | F96: Connor Haley states that heavy borrowing means even a well-run company can be wiped out by a shock it didn't cause, because debt leaves no time to wait for normal conditions. A mentioned example: a restaurant stock that borrowed for an acquisition just before COVID; its CEO talked of selling wine inventory for cash, so Alta Fox sold. It survived, but he defends the sale. Brian Gaines states that a heavily indebted company's shares become an option bet rather than a business you can value, because with large debt against a small equity base, "the movements in the stock price don't mean much" for the company's value. A mentioned example: Movie Gallery, with $1.1 billion of debt against 30 million shares. | G96: Downside protection. | H96: Easy | I96: Rare: debt in non-standard tags or D&A untagged -> flagged.
A97: Owner-Operators | B97: O9 | C97: Size (market cap) | D97: Market cap >= $100M | E97: Tradeability | F97: No investor source: a minimum market value keeps out stocks too small to buy without moving the price. | G97: Tradeable size. | H97: Partly | I97: Price x SEC share count. Unreliable for ADRs (ADR ratio unknown), multi-class shares or missing share counts -> 'check manually' (~150 ADRs last run).
A98: Owner-Operators | B98: O10 | C98: Liquidity | D98: Avg daily value traded >= $100k | E98: Tradeability | F98: No investor source: enough daily trading is needed to get in and out without a big price impact. | G98: Tradeable. | H98: Easy
A99: Owner-Operators | B99: O11 | C99: Valuation | D99: EV / EBIT <= 20x | E99: Valuation | F99: Murray Stahl states that owner-operators often carry the lowest valuations, something he said shouldn't exist yet does, because float-weighted index money underweights firms with large insider stakes, so fewer buyers bid them up. A price cap therefore rarely shuts out good owner-operators. No specific past example given. Joel Greenblatt states that price should be judged as enterprise value against pre-tax operating profit (EBIT), because that compares companies fairly whatever their debt and tax; even 12x EBIT needs a pretty good business. A mentioned example: he bought Moody's at a P/E of 20, not what he would normally do, because the business was so good. | G99: Entry discount the thesis relies on. | H99: Partly | I99: Price x SEC share count. Unreliable for ADRs (ADR ratio unknown), multi-class shares or missing share counts -> 'check manually' (~150 ADRs last run).
A100: Owner-Operators | B100: Flag | C100: Margin collapse / revenue shrinking | D100: As in Core | E100: Warning | F100: Murray Stahl states that flat revenues, rising costs, too much debt and near-term maturities mark a bad company (from a 1985 lecture recalled by co-founder Steven Bregman), because shrinking sales and squeezed margins leave less cash to meet obligations. No specific past example given. Brian Gaines states that a sudden drop in profit per sale can mean the business economics are broken, because a dominant rival's price move can permanently cut what each sale earns. A mentioned example: when Blockbuster dropped late fees he worked out gross profit per movie falling to about $1.69, called the business "absolutely destroyed" and sold Movie Gallery. Joel Greenblatt, passing on a question Rich Pzena asks, states that a troubled stock needs one answer: is the problem temporary or permanent, because temporary problems can recover while permanent ones keep eroding value. No specific past example given. | G100: Early warning. | H100: No | I100: Detected automatically; temporary vs permanent needs a human.
...

Sheet Valuation
A1: Screen | B1: 'Cheap enough' rule (pass/fail) | C1: Kind | D1: Vs peers | E1: Vs own history | F1: Implied return / DCF
A2: Core Compounders | B2: None (price-blind) | C2: - | D2: Shown on site (industry median, green/red); not a rule | E2: No | F2: No
A3: Emerging Compounders | B3: EV/EBITDA <= 20x | C3: Absolute multiple | D3: Shown on site (industry median, green/red); not a rule | E3: No | F3: No
A4: Special Situations | B4: EV/EBIT <= 15x | C4: Absolute multiple | D4: Shown on site (industry median, green/red); not a rule | E4: No | F4: No
A5: Fortress | B5: None (price-blind) | C5: - | D5: Shown on site (industry median, green/red); not a rule | E5: No | F5: No
A6: Healthcare - Commercial | B6: None (price-blind) | C6: - | D6: Shown on site (industry median, green/red); not a rule | E6: No | F6: No
A7: Healthcare - Clinical | B7: EV/cash <= 0.25 | C7: Asset floor | D7: Shown on site (industry median, green/red); not a rule | E7: No | F7: No
A8: Cyclicals | B8: EV / 10-yr avg EBIT <= 12x | C8: Absolute, on normalized earnings | D8: Shown on site (industry median, green/red); not a rule | E8: No | F8: No
A9: Owner-Operators | B9: EV/EBIT <= 20x | C9: Absolute multiple | D9: Shown on site (industry median, green/red); not a rule | E9: No | F9: No
A10: Hard Assets & Royalties | B10: EV/EBIT <= 25x | C10: Absolute multiple | D10: Shown on site (industry median, green/red); not a rule | E10: No | F10: No
A11: Asset-Floor Value | B11: Mcap <= net cash, or P/TBV <= 1.0x | C11: Asset floor | D11: Shown on site (industry median, green/red); not a rule | E11: No | F11: No
A12: Trough Cyclical Cash | B12: 5-yr avg FCF yield >= 10% | C12: Absolute, on cycle-average cash | D12: Shown on site (industry median, green/red); not a rule | E12: No | F12: No
... A14: Red Flags (avoid) | B14: EV/sales >= 6x (expensive = flag) | C14: Absolute multiple | D14: Shown on site (industry median, green/red); not a rule | E14: No | F14: No
A16: Answer: 9 of 13 screens have an absolute 'cheap enough' rule. None compares price to peers or to the company's own past multiples as a pass/fail rule.
A17: Core, Fortress and HC Commercial are price-blind by design: they show P/E, EV/EBITDA, FCF yield and peer medians, but never exclude on price.
A18: Possible adds: (1) peer-relative rule, e.g. EV/EBIT <= industry median (data already computed); (2) FCF-yield hurdle for Core/Fortress/HC; (3) own 5-10 yr multiple percentile (needs multi-year price history, not stored now).

Sheet Summary
A1: Screen | B1: Easy | C1: Partly | D1: No | E1: n/a | F1: Total | G1: % Easy
A2: Core Compounders | B2: =COUNTIFS(Criteria!$A$2:$A$158,$A2,Criteria!$H$2:$H$158,"Easy") -> 10 | C2: =COUNTIFS(Criteria!$A$2:$A$158,$A2,Criteria!$H$2:$H$158,"Partly") -> 0 | D2: =COUNTIFS(Criteria!$A$2:$A$158,$A2,Criteria!$H$2:$H$158,"No") -> 4 | E2: =COUNTIFS(Criteria!$A$2:$A$158,$A2,Criteria!$H$2:$H$158,"n/a") -> 1 | F2: =SUM(B2:E2) -> 15 | G2: =IF(F2=0,0,B2/F2) -> 0.66666667
A3: Emerging Compounders | B3: =COUNTIFS(Criteria!$A$2:$A$158,$A3,Criteria!$H$2:$H$158,"Easy") -> 9 | C3: =COUNTIFS(Criteria!$A$2:$A$158,$A3,Criteria!$H$2:$H$158,"Partly") -> 5 | D3: =COUNTIFS(Criteria!$A$2:$A$158,$A3,Criteria!$H$2:$H$158,"No") -> 1 | E3: =COUNTIFS(Criteria!$A$2:$A$158,$A3,Criteria!$H$2:$H$158,"n/a") -> 0 | F3: =SUM(B3:E3) -> 15 | G3: =IF(F3=0,0,B3/F3) -> 0.6
A4: Special Situations | B4: =COUNTIFS(Criteria!$A$2:$A$158,$A4,Criteria!$H$2:$H$158,"Easy") -> 2 | C4: =COUNTIFS(Criteria!$A$2:$A$158,$A4,Criteria!$H$2:$H$158,"Partly") -> 5 | D4: =COUNTIFS(Criteria!$A$2:$A$158,$A4,Criteria!$H$2:$H$158,"No") -> 1 | E4: =COUNTIFS(Criteria!$A$2:$A$158,$A4,Criteria!$H$2:$H$158,"n/a") -> 0 | F4: =SUM(B4:E4) -> 8 | G4: =IF(F4=0,0,B4/F4) -> 0.25
A5: Fortress | B5: =COUNTIFS(Criteria!$A$2:$A$158,$A5,Criteria!$H$2:$H$158,"Easy") -> 12 | C5: =COUNTIFS(Criteria!$A$2:$A$158,$A5,Criteria!$H$2:$H$158,"Partly") -> 2 | D5: =COUNTIFS(Criteria!$A$2:$A$158,$A5,Criteria!$H$2:$H$158,"No") -> 2 | E5: =COUNTIFS(Criteria!$A$2:$A$158,$A5,Criteria!$H$2:$H$158,"n/a") -> 1 | F5: =SUM(B5:E5) -> 17 | G5: =IF(F5=0,0,B5/F5) -> 0.70588235
A6: Healthcare - Commercial | B6: =COUNTIFS(Criteria!$A$2:$A$158,$A6,Criteria!$H$2:$H$158,"Easy") -> 10 | C6: =COUNTIFS(Criteria!$A$2:$A$158,$A6,Criteria!$H$2:$H$158,"Partly") -> 0 | D6: =COUNTIFS(Criteria!$A$2:$A$158,$A6,Criteria!$H$2:$H$158,"No") -> 2 | E6: =COUNTIFS(Criteria!$A$2:$A$158,$A6,Criteria!$H$2:$H$158,"n/a") -> 1 | F6: =SUM(B6:E6) -> 13 | G6: =IF(F6=0,0,B6/F6) -> 0.76923077
A7: Healthcare - Clinical | B7: =COUNTIFS(Criteria!$A$2:$A$158,$A7,Criteria!$H$2:$H$158,"Easy") -> 5 | C7: =COUNTIFS(Criteria!$A$2:$A$158,$A7,Criteria!$H$2:$H$158,"Partly") -> 2 | D7: =COUNTIFS(Criteria!$A$2:$A$158,$A7,Criteria!$H$2:$H$158,"No") -> 1 | E7: =COUNTIFS(Criteria!$A$2:$A$158,$A7,Criteria!$H$2:$H$158,"n/a") -> 0 | F7: =SUM(B7:E7) -> 8 | G7: =IF(F7=0,0,B7/F7) -> 0.625
A8: Cyclicals | B8: =COUNTIFS(Criteria!$A$2:$A$158,$A8,Criteria!$H$2:$H$158,"Easy") -> 8 | C8: =COUNTIFS(Criteria!$A$2:$A$158,$A8,Criteria!$H$2:$H$158,"Partly") -> 1 | D8: =COUNTIFS(Criteria!$A$2:$A$158,$A8,Criteria!$H$2:$H$158,"No") -> 1 | E8: =COUNTIFS(Criteria!$A$2:$A$158,$A8,Criteria!$H$2:$H$158,"n/a") -> 0 | F8: =SUM(B8:E8) -> 10 | G8: =IF(F8=0,0,B8/F8) -> 0.8
A9: Owner-Operators | B9: =COUNTIFS(Criteria!$A$2:$A$158,$A9,Criteria!$H$2:$H$158,"Easy") -> 9 | C9: =COUNTIFS(Criteria!$A$2:$A$158,$A9,Criteria!$H$2:$H$158,"Partly") -> 3 | D9: =COUNTIFS(Criteria!$A$2:$A$158,$A9,Criteria!$H$2:$H$158,"No") -> 2 | E9: =COUNTIFS(Criteria!$A$2:$A$158,$A9,Criteria!$H$2:$H$158,"n/a") -> 0 | F9: =SUM(B9:E9) -> 14 | G9: =IF(F9=0,0,B9/F9) -> 0.64285714
A10: Hard Assets & Royalties | B10: =COUNTIFS(Criteria!$A$2:$A$158,$A10,Criteria!$H$2:$H$158,"Easy") -> 9 | C10: =COUNTIFS(Criteria!$A$2:$A$158,$A10,Criteria!$H$2:$H$158,"Partly") -> 2 | D10: =COUNTIFS(Criteria!$A$2:$A$158,$A10,Criteria!$H$2:$H$158,"No") -> 1 | E10: =COUNTIFS(Criteria!$A$2:$A$158,$A10,Criteria!$H$2:$H$158,"n/a") -> 0 | F10: =SUM(B10:E10) -> 12 | G10: =IF(F10=0,0,B10/F10) -> 0.75
A11: Asset-Floor Value | B11: =COUNTIFS(Criteria!$A$2:$A$158,$A11,Criteria!$H$2:$H$158,"Easy") -> 8 | C11: =COUNTIFS(Criteria!$A$2:$A$158,$A11,Criteria!$H$2:$H$158,"Partly") -> 2 | D11: =COUNTIFS(Criteria!$A$2:$A$158,$A11,Criteria!$H$2:$H$158,"No") -> 1 | E11: =COUNTIFS(Criteria!$A$2:$A$158,$A11,Criteria!$H$2:$H$158,"n/a") -> 0 | F11: =SUM(B11:E11) -> 11 | G11: =IF(F11=0,0,B11/F11) -> 0.72727273
A12: Trough Cyclical Cash | B12: =COUNTIFS(Criteria!$A$2:$A$158,$A12,Criteria!$H$2:$H$158,"Easy") -> 7 | C12: =COUNTIFS(Criteria!$A$2:$A$158,$A12,Criteria!$H$2:$H$158,"Partly") -> 5 | D12: =COUNTIFS(Criteria!$A$2:$A$158,$A12,Criteria!$H$2:$H$158,"No") -> 1 | E12: =COUNTIFS(Criteria!$A$2:$A$158,$A12,Criteria!$H$2:$H$158,"n/a") -> 0 | F12: =SUM(B12:E12) -> 13 | G12: =IF(F12=0,0,B12/F12) -> 0.53846154
A13: Hidden Earnings | B13: =COUNTIFS(Criteria!$A$2:$A$158,$A13,Criteria!$H$2:$H$158,"Easy") -> 9 | C13: =COUNTIFS(Criteria!$A$2:$A$158,$A13,Criteria!$H$2:$H$158,"Partly") -> 3 | D13: =COUNTIFS(Criteria!$A$2:$A$158,$A13,Criteria!$H$2:$H$158,"No") -> 1 | E13: =COUNTIFS(Criteria!$A$2:$A$158,$A13,Criteria!$H$2:$H$158,"n/a") -> 0 | F13: =SUM(B13:E13) -> 13 | G13: =IF(F13=0,0,B13/F13) -> 0.69230769
A14: Red Flags (avoid) | B14: =COUNTIFS(Criteria!$A$2:$A$158,$A14,Criteria!$H$2:$H$158,"Easy") -> 4 | C14: =COUNTIFS(Criteria!$A$2:$A$158,$A14,Criteria!$H$2:$H$158,"Partly") -> 3 | D14: =COUNTIFS(Criteria!$A$2:$A$158,$A14,Criteria!$H$2:$H$158,"No") -> 1 | E14: =COUNTIFS(Criteria!$A$2:$A$158,$A14,Criteria!$H$2:$H$158,"n/a") -> 0 | F14: =SUM(B14:E14) -> 8 | G14: =IF(F14=0,0,B14/F14) -> 0.5
A15: All screens | B15: =SUM(B2:B14) -> 102 | C15: =SUM(C2:C14) -> 33 | D15: =SUM(D2:D14) -> 19 | E15: =SUM(E2:E14) -> 3 | F15: =SUM(F2:F14) -> 157 | G15: =IF(F15=0,0,B15/F15) -> 0.64968153
A17: Legend
A18: Easy | B18: Checked automatically from SEC XBRL / price data and reliable for nearly all companies; rare exceptions are auto-flagged.
A19: Partly | B19: Automatic for most, but a known group (ADRs, multi-class shares, foreign filers, untagged items) lands in 'check manually'.
A20: No | B20: Not checked by numbers: warning flags or judgment items for the AI review + you.
A21: n/a | B21: No rule (price-blind screens).
A22: Rationale | B22: Format: investor states that X means Y, because Z; example. Checked against all 146 transcripts. 'No investor source' = practical data rule.
A23: Note | B23: Each row is in config.json; thresholds can be changed there. Counts like '~150' are from the 7 Oct 2026 check-manually report.
